openwebinars/Openwebinar.py
openwebinars/__init__.py
openwebinars/__main__.py
taller_openwebinar-2.0.0.dist-info/LICENSE
taller_openwebinar-2.0.0.dist-info/METADATA
taller_openwebinar-2.0.0.dist-info/WHEEL
taller_openwebinar-2.0.0.dist-info/entry_points.txt
taller_openwebinar-2.0.0.dist-info/top_level.txt
taller_openwebinar-2.0.0.dist-info/RECORD
