Metadata-Version: 2.1
Name: taller-openwebinar
Version: 2.0.0
Summary: Definicion de Openwebinar
Home-page: https://github.com/Tlalocan-Courses/Taller-publica-un-paquete-en-Pypi
Author: OpenWebinars
Author-email: openwebinars@openwebinars.net
License: MIT
Platform: UNKNOWN
Classifier: License :: OSI Approved :: MIT License
Classifier: Programming Language :: Python :: 3
Classifier: Programming Language :: Python :: 3.8
Requires-Dist: python-string-utils
